{
    "date": "09-06-2021 15:33:56",
    "link": "https://de.wikipedia.org/wiki/All%5FNight%5FLong%5F3",
    "title": "All Night Long 3",
    "category": "Splatterfilm",
    "text": "Kikuo arbeitet in der Putzkolonne eines Stundenhotels. Er ist leicht geistig behindert und hat eine Vorliebe f\u00fcr fleischfressende Pflanzen. F\u00fcr diese h\u00e4ngt er in der ganzen Stadt Fliegenf\u00e4nger auf, um sie zu f\u00fcttern. Bei einer seiner \u00fcblichen Touren st\u00f6\u00dft er auf den M\u00fcllsack von Hitomi Nomura. Er verliebt sich in sie und beginnt nun zum Dreckj\u00e4ger zu werden. Er sammelt ihren M\u00fcll und wertet ihn nach pers\u00f6nlichen Daten aus. Dabei lernt er einen weiteren Dreckj\u00e4ger kennen.\nEinige seiner Arbeitskollegen vertreiben sich die Zeit mit Spannen bei den Liebespaaren. Einmal wird er von einem Mitarbeiter mitgenommen, wie er eine geistig und k\u00f6rperlich Behinderte sexuell ausnutzt und danach sadistisch qu\u00e4lt. Seine Arbeitskollegen machen sich sp\u00e4ter auch einen Spa\u00df daraus, eine Frau zu qu\u00e4len, die ihren Liebhaber im Stundenhotel ausgeraubt hat. Sie vergewaltigen sie und qu\u00e4len sie anschlie\u00dfend, bis einer sie versehentlich bewusstlos schl\u00e4gt. Kikuo nimmt sie mit nach Hause und fesselt sie ans Bett. Dann beginnt er auch, deren Daten auszuwerten. Er qu\u00e4lt sie auf verschiedene Arten und als sie zu stinken beginnt, versucht er sie mit WC-Reiniger und Desinfektionsspray zu behandeln. Dabei bemerkt er, dass Hitomi in der Drogerie arbeitet. Zu sch\u00fcchtern, sie anzusprechen, kauft er immer wieder bei ihr ein. \nAls die ans Bett gefesselte Frau sich wehrt, t\u00f6tet er sie und zerst\u00fcckelt sie anschlie\u00dfend. Beim Vergraben der Leiche wird er von seinem Dreckj\u00e4ger-Kollegen erwischt, der ihn zu einem Brennofen f\u00fchrt, wo er ihre \u00dcberreste entsorgt. Auch ihn t\u00f6tet Kikuo schlie\u00dflich und \u00fcbernimmt anschlie\u00dfend sein Versteck, wo er eine Waffe findet.\nBei einer Schicht im Stundenhotel kommt Hitomi mit einem Mann herein. Kikuo wird fast wahnsinnig. Dies bekommen seine Arbeitskollegen mit. Sie entf\u00fchren den Mann und Hitomi und bringen beide zum Versteck des anderen Dreckj\u00e4gers. Dort missbrauchen sie zun\u00e4chst den Mann, bis Kikuo erscheint und alle t\u00f6tet. \nDie letzte Szene zeigt, wie Hitomi in einem M\u00fcllsack in Kikuos Wohnung aufwacht. Kikuo aktualisiert ihre Daten.\n"
}