{
    "date": "09-06-2021 15:34:37",
    "link": "https://de.wikipedia.org/wiki/American%5FHoney%5F%28Film%29",
    "title": "American Honey (Film)",
    "category": "Roadmovie",
    "text": "Die achtzehnj\u00e4hrige Star lebt in prek\u00e4ren Verh\u00e4ltnissen in Oklahoma, nachdem ihre Mutter es vorgezogen hat, ein Leben ohne ihre Tochter zu f\u00fchren. Gemeinsam mit ihren beiden Halbgeschwistern fristet Star ein trauriges Leben bei ihrem Stiefvater, der nicht davor zur\u00fcckschreckt, sich der jungen Frau in sexistischer Weise zu n\u00e4hern. \nAls sie Jake trifft, einen jungen Mann, der mit einer jugendlichen \u201eDr\u00fcckerkolonne\u201c durchs Land reist, schlie\u00dft sie sich der Gruppe kurzerhand an. Gemeinsam beginnt ein Roadtrip durch den Mittleren Westen. Tags\u00fcber versuchen die Jugendlichen bei Haust\u00fcrgesch\u00e4ften Zeitschriftenabonnements zu verkaufen, die N\u00e4chte verbringen sie mit Alkohol und Partys.\n"
}