{
    "date": "09-06-2021 15:33:56",
    "link": "https://de.wikipedia.org/wiki/Angriff%5Fder%5FLederhosenzombies",
    "title": "Angriff der Lederhosenzombies",
    "category": "Splatterfilm",
    "text": "Der Tiroler Unternehmer Franz Steiner entwickelt einen w\u00e4rmebest\u00e4ndigen Kunstschnee aus einer giftig-gr\u00fcn fluoreszierenden Substanz namens Solanum +10, den er an den Investor Chekov, einen Russen, verkauft. Als dieser bei einer Vorf\u00fchrung an der Skipiste mit der Substanz in Ber\u00fchrung kommt, bekommt er gro\u00dfe Pusteln und muss sich \u00fcbergeben, wobei ein gr\u00fcner Strahl seinem Mund entweicht. Etwas sp\u00e4ter kann er nur noch grunzen, wenn er versucht zu sprechen.\nAuch andere G\u00e4ste, die in Ritas Gaudih\u00fctte mit dem sogenannten Kunstschnee in Ber\u00fchrung kommen, machen eine Ver\u00e4nderung durch und werden zu torkelnden, schleimkotzenden Zombies. Sie sind jedoch von den Alkoholleichen, die einem beim Apr\u00e8s-Ski \u00fcber den Weg laufen, nur schwer zu unterscheiden, sodass die besorgniserregende Transformation zun\u00e4chst nicht weiter auff\u00e4llt. So verwandelt der Untote Chekov die Angetrunkenen, die um ihn herum feiern, nach und nach in blutr\u00fcnstige Zombies.\nDer Profi-Extremsnowboarder Steve hat bei einem Werbespot versagt und die Aufnahmen ruiniert, was dazu f\u00fchrte, dass man ihn, seine Freundin Branka und seinen Kollegen Josh in den Bergen zur\u00fcckgelassen hat. Auf der Suche nach einem Unterschlupf landen die drei in der Gaudih\u00fctte, wo die Feiernden das Saisonende begie\u00dfen. Als ihnen bewusst wird, das hier etwas ganz und gar nicht stimmt, verschanzen sie sich zuerst hinter den Bierb\u00e4nken, verteidigen sich sodann mit scharfkantigen Snowboards, Skist\u00f6cken und greifen zuletzt auf Motors\u00e4gen und Schneefr\u00e4sen zur\u00fcck, um einer Transformation zu entgehen. Gaudiwirtin Rita ist ihnen dabei eine wertvolle Hilfe.\n"
}