{
    "date": "09-06-2021 15:39:22",
    "link": "https://de.wikipedia.org/wiki/Black%5FDynamite",
    "title": "Black Dynamite",
    "category": "Martial-Arts-Film",
    "text": "Der Film spielt in den 1970er-Jahren. Black Dynamite, ein Vietnamveteran und ehemaliger CIA-Agent, hat es sich zur Aufgabe gemacht, die Stra\u00dfen von Drogendealern und Verbrechern zu s\u00e4ubern, nachdem sein j\u00fcngerer Bruder Jimmy von einer Unterweltorganisation ermordet wurde. O\u2019Leary, ein Freund aus seiner Milit\u00e4r- und CIA-Zeit, macht ihn wieder zu einem Agenten, da er verhindern will, dass Black Dynamite Selbstjustiz ver\u00fcbt. W\u00e4hrend er den Tod seines Bruders untersucht, erf\u00e4hrt Black Dynamite, dass dieser als Undercover-Agent ebenfalls f\u00fcr die CIA gearbeitet hat. Black Dynamite findet heraus, dass die kriminelle Vereinigung, die f\u00fcr den Tod seines Bruders verantwortlich ist, auch Waisenh\u00e4user, in denen vornehmlich afroamerikanische Kinder aufgenommen werden, mit Heroin versorgt. Er sagt den \u00f6rtlichen Drogenh\u00e4ndlern den Kampf an, was ihm die Zuneigung von Gloria einbringt, einer Black Power-Aktivistin, die in einem dieser Waisenh\u00e4user arbeitet.\nNachdem er Rafelli, einen der Drahtzieher des Drogenhandels, get\u00f6tet und entdeckt hat, dass die Regierung in den Drogenring verwickelt ist, stiehlt Black Dynamite die Aufzeichnungen des korrupten Kongressabgeordneten James, in denen Details \u00fcber illegale Lieferungen, Handelsrouten und Lagerh\u00e4user enthalten sind. Black Dynamite st\u00fcrmt mit seinem Freund Bullhorn, dem Kleinkriminellen Cream Corn, dem Black-Power-Anf\u00fchrer Saheed, Gunsmoke und zwei weiteren Aktivisten zwei Lagerh\u00e4user, um eine gro\u00dfe Drogenlieferung abzufangen. Sie finden zwar keine Drogen, aber Informationen \u00fcber die Geheimoperation \u201eCode Kansas\u201c und eine gr\u00f6\u00dfere Menge Malt liquor der Marke \"Anaconda\". Diese von der Regierung hergestellte Marke ist f\u00fcr ihren Werbeslogan \u201eGives You Ooooooo!\u201c bekannt. In einem Imbissrestaurant entschl\u00fcsseln sie den Werbeslogan und decken den Plan der Operation \u201eCode Kansas\u201c auf: afroamerikanische M\u00e4nner sollen buchst\u00e4blich \u201eentmannt\u201c werden, da der Konsum dieses Malt liquor die den Penis schrumpfen lassen soll \u2013 \u201eAnaconda Malt Liquor gives you a little dick\u201c. Gunsmoke, einer der Aktivisten, der bereits Opfer des Plans wurde, wird von seinen Freunden get\u00f6tet, um ihn von seinem \u201eLeid\u201c zu erl\u00f6sen. Die Gruppe kehrt in das Lagerhaus zur\u00fcck, wo sich herausstellt, dass O\u2019Leary Teil der Operation \u201eCode Kansas\u201c ist. Black Dynamite t\u00f6tet ihn und findet einen weiteren Hinweis auf die Geheimoperation.\nBlack Dynamite begibt sich nach Kung Fu Island, wo er entdeckt, dass sein alter Erzfeind Dr. Wu f\u00fcr die Entwicklung der Geheimformel von \u201eAnaconda Malt Liquor\u201c verantwortlich ist. Nach einem harten Kampf, in dem Saheed, die beiden Aktivisten und Bullhorn sterben, t\u00f6tet Black Dynamite Dr. Wu und deckt den wahren Drahtzieher des Plans auf: das Wei\u00dfe Haus.\nBlack Dynamite reist mit einem Helikopter zum Wei\u00dfen Haus, wo Cream Corn von Agenten des United States Secret Service get\u00f6tet wird. Er konfrontiert Pr\u00e4sident Richard Nixon, der in der Geheimoperation von Anfang an die F\u00e4den gezogen hat. Black Dynamite besiegt Nixon in einem Kung-Fu-Kampf und droht damit, Nixon mit Bondage- und Cross-Dressing-Fotos blo\u00dfzustellen. Nixon bittet Black Dynamite, ihn lieber zu t\u00f6ten; dieser lehnt dies aber ab und fordert ihn stattdessen auf, sich um \u201eseine Leute\u201c zu k\u00fcmmern. Der Film endet mit einem Monolog von Black Dynamite \u00fcber seinen Feldzug f\u00fcr die Gerechtigkeit, w\u00e4hrend ihm Gloria und Pat Nixon zu F\u00fc\u00dfen liegen und ihn schmachtend ansehen.\n"
}