{
    "date": "09-06-2021 15:36:19",
    "link": "https://de.wikipedia.org/wiki/Das%5Fkalte%5FHerz%5F%282013%29",
    "title": "Das kalte Herz (2013)",
    "category": "M\u00e4rchenfilm",
    "text": "Peter Munk ist schwarz durch seine Arbeit mit Kohlen. Als er eines Tages Gefallen an Lisbeth gefunden hat, m\u00f6chte er sein Leben als \u201eKohlenpeter\u201c \u2013 so wird er von den Leuten nur genannt \u2013 aufgeben und macht sich als Sonntagskind zum Glasm\u00e4nnlein auf. Dort wei\u00df er den Vers nicht bis zum Ende und gelangt in das Reich des Holl\u00e4nder-Michel.\n"
}