{
    "date": "09-06-2021 15:39:25",
    "link": "https://de.wikipedia.org/wiki/Das%5FSchwert%5Fdes%5Fgelben%5FTigers",
    "title": "Das Schwert des gelben Tigers",
    "category": "Martial-Arts-Film",
    "text": "Der junge, begabte Schwertk\u00e4mpfer Lei Li l\u00e4sst sich auf einen Kampf mit dem viel erfahreneren Fechtmeister Lung, dem Herrn der Tigerburg, ein, den er aber verliert. Aufgrund eines Schwurs schl\u00e4gt sich der junge Mann daraufhin den rechten Arm ab und schw\u00f6rt, nie wieder zu k\u00e4mpfen. Er zieht sich zur\u00fcck und arbeitet in einem Gasthaus, wo er von den G\u00e4sten verspottet wird, aber auch in Pa Hsiao, der Tochter des Schmieds, die gro\u00dfe Liebe findet. Schlie\u00dflich kommt ein junger Schwertk\u00e4mpfer namens Feng in die Gegend, der den Verbrechen, welche im Land immer mehr \u00fcberhandnehmen, auf den Grund gehen will. Er freundet sich mit Lei Li an, geht aber schlie\u00dflich doch gegen dessen Rat auf die Tigerburg, wo er den Ursprung der Verbrechen vermutet und wird dort nach einem langen, blutigen Kampf durch Meister Lung get\u00f6tet.\nLei Li schw\u00f6rt daraufhin Rache und st\u00fcrmt allein die Tigerburg, indem er alle darin befindlichen M\u00e4nner t\u00f6tet. Schlie\u00dflich kommt es zum finalen Duell zwischen ihm und Lung und es gelingt Lei Li, den Feind zu \u00fcberlisten und zu besiegen. Pa Hsiao kommt dazu und die beiden verlassen gemeinsam die mit Leichen gef\u00fcllte Tigerburg.\n"
}