{
    "date": "09-06-2021 15:38:25",
    "link": "https://de.wikipedia.org/wiki/Der%5FMann%2C%5Fder%5Fzum%5FEssen%5Fkam",
    "title": "Der Mann, der zum Essen kam",
    "category": "Weihnachtsfilm",
    "text": "Der egozentrische, anspruchsvolle und zynische Radiostar Sheridan Whiteside aus New York City befindet sich wenige Wochen vor Weihnachten auf einer Lesereise durch die Vereinigten Staaten. Bei einem geplanten Essen mit den Stanleys, einer angesehenen Familie in einem Provinznest in Ohio, rutscht er auf deren vereisten Hausstufen aus. Whiteside wird \u00e4rztlich angewiesen, sich nun mehrere Wochen im Haus der Stanleys von den Folgen zu erholen, was ihn prompt dazu veranlasst, dem Familienvater Mr. Stanley mit einer Klage in H\u00f6he von 150.000 Dollar zu drohen. Das exzentrische Verhalten von Whiteside sorgt bei dem biederen Ehepaar Stanley f\u00fcr b\u00f6se \u00dcberraschungen, etwa, wenn er sich aus dem Gef\u00e4ngnis M\u00f6rder zum Mittagessen einl\u00e4dt oder sich Oktopusse und Pinguine ins Haus bestellt. Zudem sorgt Whiteside daf\u00fcr, dass die jugendlichen Kinder der Stanleys gegen ihre Eltern rebellieren: W\u00e4hrend Sohn Richard nun unbedingt Fotograf und kein Gesch\u00e4ftsmann werden will, versucht Tochter June, den von ihrem Vater verhassten Gewerkschafter Sandy zu heiraten. Nur Mutter Harriet genie\u00dft hin und wieder, dass ihr Name nun durch den Unfall prominent in allen Zeitungen des Landes erw\u00e4hnt wird.\nSeit neun Jahren ist Maggie Cutler die pers\u00f6nliche Sekret\u00e4rin von Sheridan, der er als eine der wenigen Personen vertraut und die zu einer wichtigen St\u00fctze f\u00fcr ihn geworden ist, was er ihr allerdings selten dankt. Maggie verliebt sich w\u00e4hrend des Aufenthalts in den \u00f6rtlichen Zeitungsredakteur Bert Jefferson und verbringt pl\u00f6tzlich weniger Zeit mit Sheridan, was diesen sehr \u00e4rgert. Auf Nachfrage von Sheridan erkl\u00e4rt Maggie, dass sie Bert heiraten und ihre Anstellung bei ihm binnen kurzer Zeit k\u00fcndigen wolle. Der Star g\u00f6nnt ihr allerdings nicht das pers\u00f6nliche Gl\u00fcck, da er sie f\u00fcr unverzichtbar an seiner Seite h\u00e4lt, und leitet Ma\u00dfnahmen ein, das frische Liebesgl\u00fcck zu sabotieren. Bert hat n\u00e4mlich ein Theaterst\u00fcck geschrieben, welches er gerne auf die B\u00fchne bringen will. Sheridan l\u00e4dt die glamour\u00f6se Broadway-Schauspielerin Lorraine Sheldon, die schon viele M\u00e4nnerherzen gebrochen hat, an Weihnachten zu sich ein. Lorraine soll mit Bert \u00fcber das St\u00fcck reden und ihm dabei den Kopf verdrehen, so dass er nicht mehr an Maggie denkt. Sheridan erf\u00e4hrt inzwischen, dass er leichter verletzt ist als gedacht und durchaus laufen kann, was er aber f\u00fcr seine Pl\u00e4ne vor Maggie und den Stanleys geheim h\u00e4lt.\nMaggie hat allerdings neun Jahre Erfahrung mit Sheridan und ahnt schon fr\u00fch seine Intrige. Ihr guter Freund, der Autor Beverly Carlton, ahmt Lorraines neuesten Million\u00e4rsvereherer Lord Bottomley am Telefon nach: Er wolle sie endlich heiraten, weshalb sie doch auf schnellem Wege zu ihm reisen solle. Doch der Plan fliegt auf und Lorraine ist nun noch zielstrebiger, Maggie ihren Geliebten wegzuschnappen. Tats\u00e4chlich scheint Whitesides Plan aufzugehen, da ein betrunkener Bert am Morgen nach Weihnachten ank\u00fcndigt, mit Lorraine f\u00fcr ein paar Wochen wegzufahren, um an dem St\u00fcck zu arbeiten. Doch Maggie k\u00fcndigt ihren Job bei Sheridan auch so und wirft ihm seine Selbstsucht vor. Inzwischen erscheint Banjo, ein Freund von Whiteside aus Hollywood, der ihm ins Gewissen redet. Nun wollen Banjo und Whiteside die Pl\u00e4ne von Lorraine doch noch durchkreuzen. Die ahnungslose Schauspielerin wird in einen Sarkophag gesteckt, der von Banjo aus dem Haus der Stanleys getragen wird. Dem Gl\u00fcck von Maggie und Bert steht nun nichts mehr im Weg.\nAber auch Whitesides Zeit im Haus der Stanleys scheint vor\u00fcber: Familienvater Ernest hat genug von den Beleidigungen und Eskapaden des Simulanten, vor allem nachdem er June und Richard angestiftet hat, von ihrem Elternhaus wegzulaufen. Er verweist Whiteside mit Unterst\u00fctzung des Sheriffs des Hauses. Whiteside konfrontiert Mr. Stanley allerdings zuvor mit seiner seltsam erscheinenden Schwester Harriet, in der er \u2013 f\u00fchrender Experte auf dem Gebiet von Morden \u2013 eine ehemalige, legend\u00e4re Axtm\u00f6rderin erkennt. Damit das Familiengeheimnis ein Geheimnis bleibt, erpresst Whiteside, dass Stanleys Kinder ihren eigenen Weg gehen d\u00fcrfen und nicht den vorgeschriebenen ihres Vaters. Whiteside verl\u00e4sst das Haus, doch pl\u00f6tzlich ruft Mrs. Roosevelt an, um Weihnachtsgr\u00fc\u00dfe zu \u00fcbermitteln. Die aufgeregte Mrs. Stanley ruft Sheridan ans Telefon zur\u00fcck, woraufhin er auf der Treppe ausrutscht. Zum Schrecken von Mr. und Mrs. Stanley geht damit alles von vorne los ...\n"
}