{
    "date": "09-06-2021 15:37:21",
    "link": "https://de.wikipedia.org/wiki/Die%5FBourne%5FIdentit%C3%A4t",
    "title": "Die Bourne Identit\u00e4t",
    "category": "Agentenfilm",
    "text": "Zu Beginn des Films ziehen italienische Fischer einen bewusstlosen Mann aus dem Mittelmeer. Er hat keine Erinnerung an sein fr\u00fcheres Leben, daf\u00fcr aber zwei Kugeln im R\u00fccken, unter der Haut ein Laserimplantat mit der Nummer eines Schweizer Bankschlie\u00dffachs und eine enorm gute Auffassungsf\u00e4higkeit. Auf der Suche nach seiner Identit\u00e4t findet er in Z\u00fcrich im Bankschlie\u00dffach eine Waffe, ein halbes Dutzend gef\u00e4lschter Reisep\u00e4sse und Banknoten verschiedener W\u00e4hrungen in gro\u00dfen Mengen. Im ersten Pass, einem US-amerikanischen, der separat von den anderen oben im Koffer liegt und den er als erstes aufschl\u00e4gt, steht der Name Jason Bourne.\nMit Hilfe der deutschen Weltenbummlerin Marie macht sich Jason auf den Weg nach Paris, wo er fr\u00fcher gearbeitet haben muss. Er merkt, dass er \u00fcber au\u00dfergew\u00f6hnliche Nahkampff\u00e4higkeiten und eine ebensolche Beobachtungsgabe verf\u00fcgt, die er fr\u00fcher sehr systematisch erworben haben muss. Die Concierge an der Adresse aus dem US-amerikanischen Pass in Paris erkennt ihn sofort. W\u00e4hrend er sich in seiner alten Wohnung umsieht, wird er von einem Killer \u00fcberfallen. Dieser wird im Nahkampf von Jason zur\u00fcckgeschlagen. Der Killer weigert sich, seine Auftraggeber preiszugeben und st\u00fcrzt sich schlie\u00dflich aus dem Fenster. Jason und Marie fliehen und kommen sich auf der Flucht n\u00e4her, w\u00e4hrend der CIA-Abteilungsleiter Alexander Conklin mit einem gro\u00dfen Agentenaufgebot die beiden jagt.\nJason und Marie, inzwischen verliebt, fliehen zu Maries Bekanntem Eamon aufs Land. Aber auch dort wird Jason von einem CIA-Killer aufgesp\u00fcrt, der sich \u201eDer Professor\u201c nennt. Die beiden zum T\u00f6ten ausgebildeten M\u00e4nner liefern sich ein Duell in freier Natur, bei dem Jason den \u201eProfessor\u201c t\u00f6tet. Eamon f\u00e4hrt mit seinen Kindern und Marie davon, die nach Aufforderung Jasons nur widerwillig mitf\u00e4hrt, um unterzutauchen. Jason f\u00e4hrt alleine nach Paris zur\u00fcck. Dort trifft er Conklin, den er mit vorgehaltener Waffe zum Reden bewegt.\nDurch einige Informationen, die Conklin ihm gibt, erinnert sich Jason, dass er einen afrikanischen Ex-Diktator auf dessen Yacht im Mittelmeer t\u00f6ten sollte, es aber nicht \u00fcbers Herz brachte, dies vor dessen Kindern zu tun, und fl\u00fcchtete. Auf der Flucht trafen ihn zwei Kugeln, und er st\u00fcrzte ins Wasser.\nDie Erkenntnis, dass er ein Auftragskiller der CIA mit der perfekt konstruierten Scheinidentit\u00e4t von Jason Bourne ist, trifft ihn hart. Er war Teil einer hochgeheimen Operation der CIA, des sogenannten Treadstone-Projekts.\nBourne schl\u00e4gt Conklin nieder, schaltet noch drei andere Agenten aus, die es auf ihn abgesehen haben, und flieht. Kurz darauf folgt ihm Conklin, der aber von einem anderen CIA-Killer liquidiert wird, da sein Vorgesetzter, Ward Abbott, das Scheitern des Projekts \u201eTreadstone\u201c vertuschen will.\nAnschlie\u00dfend wird der f\u00fcr das Treadstone-Projekt zust\u00e4ndige Abbott vor ein CIA-Untersuchungskomitee geladen. Dort behauptet er, das Treadstone-Projekt sei ein Projekt zur Ausbildung neuer Agenten, das sich aus finanziellen Gr\u00fcnden nicht gelohnt habe. Das Untersuchungskomitee akzeptiert diese L\u00fcge ohne weitere Nachfragen und geht zum n\u00e4chsten Thema, dem Blackbriar-Programm, \u00fcber. (Dieses Programm wird im dritten Teil \u2013 Das Bourne Ultimatum \u2013 aufgegriffen.)\nMarie ist inzwischen in Griechenland untergetaucht und betreibt eine Motorroller-Vermietung im kleinen Urlaubsort Mykonos. Der Film endet damit, dass Jason eines Tages an ihrer T\u00fcr steht und sich beide in die Arme fallen.\n"
}