{
    "date": "09-06-2021 15:39:33",
    "link": "https://de.wikipedia.org/wiki/Fireball%5F%28Film%29",
    "title": "Fireball (Film)",
    "category": "Martial-Arts-Film",
    "text": "Thailand in der Gegenwart. Str\u00e4fling Tai erlangt durch Geldzuwendungen seines Zwillingsbruders Tan Anspruch auf eine vorzeitige Haftentlassung, die ihm schlie\u00dflich gew\u00e4hrt wird. Nachfolgend besucht der ehemalige Strafgefangene seinen selbstlosen Retter. Diesen findet er mit schwersten Kopfverletzungen in einem komat\u00f6sen Zustand vor \u2013 f\u00fcrsorglich umsorgt von dessen Freundin Pang. Die wimmernde Sch\u00f6nheit ist am Boden zerst\u00f6rt. Sie f\u00fcrchtet, dass ihr Geliebter in illegale Machenschaften verstrickt sein k\u00f6nnte, da der leidenschaftliche Basketballspieler in letzter Zeit vermehrt Blessuren davontrug. Tai beschlie\u00dft der Sache nachzugehen. In einer zwielichtigen Gegend trifft er alsbald auf eine Gruppe Sportler, die ihn mit seinem bettl\u00e4gerigen Zwillingsbruder verwechseln. Sie alle sind Teil einer Fireball-Mannschaft, einer illegalen auf Basketball basierenden Kampfsportart. Tai spielt mit seiner missverst\u00e4ndlichen Identit\u00e4t, tritt in Tans Fu\u00dfstapfen und wird schlie\u00dflich Mitglied des Teams von Chefstratege Den.\nVerdeckt gelingen ihm ungew\u00f6hnliche Einblicke der Untergrund-Szene. Zudem erf\u00e4hrt er, dass Tan aktiver Fireballer war, der inmitten eines Spiels von einem Gegenspieler namens Ton verletzt wurde. Da dieser zun\u00e4chst nicht zur Rechenschaft gezogen werden kann, die Regeln verbieten eine Auseinandersetzung au\u00dferhalb des Spielfeldes, konzentriert sich der Hauptdarsteller zun\u00e4chst auf die Begegnungen des Turniers. \nDer eigentliche Wettbewerb ist kaum reglementiert; jede Form der Gewalt ist gestattet, wie auch der eingeschr\u00e4nkte Gebrauch von Waffen. Versch\u00e4rfend wirken sich ferner lukrative Wetten auf den Ausgang einer jeweiligen Partie aus. Diese Faktoren machen Fireball zu einem unerbittlichen Sport, der sogar Tote billigend in Kauf nimmt bzw. bewusst provoziert. Bereits in der zweiten Runde offenbart sich dieses Szenario. Dens Mannschaft wird eines Mitspielers beraubt, der hinterr\u00fccks ermordet wird. Als sich der Kader weiter lichtet, kommt es zu unvermeidbaren internen Querelen, die aber nur von kurzer Dauer sind. Die materiellen und finanziellen N\u00f6te zwingen die drei verbliebenen Spieler das Turnier wieder aufzunehmen. Tai ben\u00f6tigt beispielsweise Geld, um dem todkranken Bruder eine kostspielige Operation finanzieren zu k\u00f6nnen.\nIn einem finalen Spiel tritt Dens dezimiertes Team gegen eines Auswahl des Titelverteidiger an, um Tais Erzfeind Ton. Das eigentliche Spiel wird zur Nebensache. Dens Mannschaft gelingt so die Gegnerschaft in kr\u00e4ftezehrenden K\u00e4mpfen niederzustrecken \u2013 darunter auch Ton. Als Tai am Ende des Films schwer verletzt und entkr\u00e4ftet auf dem Spielfeld zu Boden sackt und stirbt, erwacht dessen Zwillingsbruder Tan wie von Geisterhand aus seinem tiefen Schlaf.\n"
}