{
    "date": "09-06-2021 15:38:44",
    "link": "https://de.wikipedia.org/wiki/Kein%5FAbend%5Fwie%5Fjeder%5Fandere",
    "title": "Kein Abend wie jeder andere",
    "category": "Weihnachtsfilm",
    "text": "Friedrich Roeder und der Brite Billy sind Antiquit\u00e4tenh\u00e4ndler. Erschwerend an dem Umstand ist, dass beide in der gleichen Stra\u00dfe ans\u00e4ssig sind, noch dazu direkt gegen\u00fcber. W\u00e4hrend Billy seinen Schwerpunkt auf den Verkauf importierter, zum Teil auch gef\u00e4lschter Ware aus Fernost legt, ist Roeder ein Antiquit\u00e4tenh\u00e4ndler der \u201ealten Schule\u201c: Er handelt nur mit Ware die einen echten Wert besitzt, deren Herkunft nachweisbar ist und somit auch relativ hochpreisig ist.\nDarunter befindet sich auch ein wertvolles b\u00f6hmisches Schachspiel aus dem 18. Jahrhundert, das offenbar zu dieser Zeit f\u00fcr August den Starken handgeschnitzt wurde. Allerdings fehlt Roeder zu diesem Spiel noch ein einziger Bauer, dessen Verbleib aber unbekannt ist.\nDie Weihnachtszeit ist gekommen, deren Feier jeder der beiden auf seine eigene Art begeht. Billy bewirtschaftet standesgem\u00e4\u00df eine schottische Dudelsackkapelle mit Whisky, die bei ihm zu Besuch ist. Roeder hingegen begeht Weihnachten auf eine etwas feinere Art: Er hat Besuch von einem Kinderchor, der Weihnachtslieder singt. Zum Dank daf\u00fcr gibt es von Roeder anschlie\u00dfend Milch mit Kakao, feine Kuchen und im Anschluss daran, eine wundervolle, weihnachtliche Bescherung. Gr\u00f6\u00dfer k\u00f6nnten die Gegens\u00e4tze zwischen den beiden folglich kaum sein.\n\u00dcberraschenderweise erh\u00e4lt Billy auch eine Einladung zu Roeders Weihnachtsfeier. Dieser kommt er dann auch, nach einigen \u00dcberlegungen nach. Nachdem Billy bei Roeder eingetroffen ist, erz\u00e4hlt Roeder auf eine ber\u00fchrende Art eine wundervolle Weihnachtsgeschichte. Daraufhin wandeln sich die ersten Eindr\u00fccke von Billy: Ihm bereitet es nun gro\u00dfes Vergn\u00fcgen, den Heiligen Abend bei Roeder zu verbringen.\nAls die Kinder gegangen sind, pr\u00e4sentiert Billy seinem Nachbarn zu dessen gro\u00dfer \u00dcberraschung den fehlenden Bauern aus dem b\u00f6hmischen Schachspiel, den er selber einmal erworben hatte.\nBeide beschlie\u00dfen, gemeinsam eine Partie Schach zu spielen, wobei Billy standesgem\u00e4\u00df seine Figuren auf einem Billig-Schachbrett aus Plastik bewegt und Roeder die seinen auf dem edlen Schachbrett aus dem 18. Jahrhundert. Dadurch bricht zwischen ihnen endg\u00fcltig das Eis. Die beiden fangen an, sich gegenseitig zu respektieren. Aus den beiden ehemaligen erbitterten Konkurrenten und grundverschiedenen Charakteren wird schlie\u00dflich sogar eine Art \u201eFreunde\u201c.\nPassend zu der Weihnachtszeit im Film wurde er an Heiligabend erstmals ausgestrahlt.\n"
}