{
    "date": "03-05-2021 12:13:26",
    "link": "https://de.wikipedia.org/wiki/Sideways",
    "title": "Sideways",
    "category": "Roadmovie",
    "text": "Sideways (dt.: \u201eseitw\u00e4rts\u201c) ist ein US-amerikanischer Spielfilm von Alexander Payne aus dem Jahr 2004. Das von Payne und Jim Taylor verfasste Drehbuch basiert auf dem gleichnamigen Roman des US-amerikanischen Schriftstellers und Drehbuchautors Rex Pickett.\nDer geschiedene Englischlehrer und Weinliebhaber Miles, der drei Jahre lang an einem Roman geschrieben hat, und sein bester Freund Jack, der sich als Schauspieler f\u00fcr Werbespots \u00fcber Wasser h\u00e4lt und dabei von einer l\u00e4ngst abgesetzten Serienrolle zehrt, unternehmen eine einw\u00f6chige Reise in die Weinanbaugebiete Kaliforniens nach Santa Ynez Valley. Beide kennen sich seit ihrer Zeit an der Universit\u00e4t von San Diego.\nMiles plant, von einem Weinberg zum n\u00e4chsten zu fahren, ausgiebige Weinproben zu genie\u00dfen, \u00fcber Wein zu philosophieren, gut zu essen und Golf zu spielen. Jack will nach der Reise seine wohlhabende armenische Freundin heiraten und dann in das Immobilienmaklerb\u00fcro seines Schwiegervaters einsteigen. Er m\u00f6chte sich auf der Reise vergn\u00fcgen und vor der Hochzeit noch ein paar Abenteuer mit Frauen haben.\nVor der eigentlichen Reise besuchen beide Miles' alleinlebende Mutter, der Miles Geld aus der Schublade stiehlt. Miles macht deutlich, dass er noch sehr unter der Scheidung von seiner Ex-Frau leidet.\nAuf der Reise treffen sie auf die Weinverk\u00e4uferin Stephanie und die Kellnerin Maya, die sich als ausgewiesene Weinkennerin entpuppt. W\u00e4hrend Jack heftig mit der lebenslustigen Stephanie flirtet, den Tag zur Nacht macht und nahe dran ist, die Hochzeit abzusagen, weil er sein Playboy-Dasein noch nicht aufgeben m\u00f6chte, verlieben sich Miles und Maya ineinander. Miles ist jedoch sch\u00fcchtern und n\u00e4hert sich ihr nur vorsichtig an.\nW\u00e4hrend eines Picknicks verr\u00e4t Miles gegen\u00fcber Maya versehentlich die anstehende Hochzeit von Jack. Maya wendet sich entt\u00e4uscht von Miles ab. Als Stephanie davon erf\u00e4hrt, wird sie w\u00fctend und bricht Jack mit einem Motorradhelm die Nase. Kurz darauf erf\u00e4hrt Miles, dass sein Roman nicht ver\u00f6ffentlicht wird. Am letzten Abend st\u00fcrzt sich Jack in ein weiteres sexuelles Abenteuer, was ihn und Miles wieder in Schwierigkeiten bringt. Er und Jack beenden ihre Reise und stellen gegen\u00fcber Jacks zuk\u00fcnftigen Schwiegereltern die gebrochene Nase als Folge eines Autounfalls dar. Auf der Hochzeit trifft Miles seine Ex-Frau Victoria wieder, die mit einem attraktiven Mann verheiratet ist und von diesem ein Kind erwartet.\nMiles fasst erst wieder Mut, als er nach einer Nachricht auf seinem Anrufbeantworter wieder Kontakt mit Maya aufnimmt. Sie hat seinen Brief und sein Manuskript gelesen, das ihr gut gefallen hat. Der Film endet, als er vor ihrer T\u00fcr steht und anklopft. Es bleibt offen, ob sie zuhause ist, ob sie ihm aufmacht und wie es mit den beiden weitergeht.\nDer Soundtrack stammt von Rolfe Kent. \nDer film-dienst schrieb, der Film sei \u201eunterhaltsam\u201c sowie \u201evoll unwiderstehlichem Charme und sanfter Lebensweisheit. Hinter der Komik der Ereignisse tritt eine liebevolle, pr\u00e4zise Beschreibung menschlicher Eigenarten und Schw\u00e4chen zutage, wie sie in Hollywood-Filmen selten anzutreffen sind.\u201c\nSpiegel Online urteilte: \u201eEs braucht nicht die elit\u00e4ren Geschmacksknospen eines Connaisseurs, um das warme Innere von Sideways zu entdecken. Auch ein Laie kann die Erfahrung dieses vollmundigen Americana-Abenteuers treffend beschreiben: Anfangs bei\u00dft es heftig auf der Zunge, doch sein Abgang ger\u00e4t unerwartet sanft.\u201c\nSideways gewann zahlreiche Auszeichnungen.\nThe Passion of Martin |\nBaby Business |\nElection |\nAbout Schmidt |\nSideways |\nParis, je t\u2019aime (Episode: 14e arrondissement) |\nThe Descendants \u2013 Familie und andere Angelegenheiten |\nNebraska |\nDownsizing\n"
}