{
    "date": "09-06-2021 15:34:28",
    "link": "https://de.wikipedia.org/wiki/The%5FHospital%5F2",
    "title": "The Hospital 2",
    "category": "Splatterfilm",
    "text": "Alan und Stanley haben die Ereignisse aus Teil 1 nicht nur \u00fcberlebt, sie sind auch weiter erfolgreich im Snuff-Gesch\u00e4ft. In einer Klinik f\u00fcr misshandelte Frauen streamen sie neue bestialische Morde und Vergewaltigungen \u00fcber das Internet. Stanley ist nun sogar Darsteller in den Filmen. M\u00f6glich gemacht hat dies Samantha, die Tochter von Alan, die in einer Art inzestu\u00f6sen Beziehung zu ihrem Erzeuger lebt und selbst Spa\u00df an Sadismus, Vergewaltigung und Mord empfindet.\nBeth und Skye, die damals aus dem Hospital fl\u00fcchten konnten, leiden beide unter einer PTBS. Beide bef\u00fcrchten auch, dass die beiden Snuff-Filmer noch am Leben sind. Skye, die mittlerweile in einer WG wohnt, f\u00e4hrt zu ihren Eltern aufs Land und versucht dort Entspannung zu finden. Stanley befindet sich jedoch schon auf ihren Fersen. Tats\u00e4chlich gelingt es ihm, die WG zu finden. Dort t\u00f6tet er ein P\u00e4rchen und findet heraus, wo sich Skye aufh\u00e4lt und wo das Haus ihrer Eltern ist.\nAls Alan von Stanleys Nachforschungen erf\u00e4hrt, ist er zun\u00e4chst wenig begeistert. Doch seine Tochter hat eine Idee. Sie schlie\u00dfen zun\u00e4chst Stanley aus, dann begeben sie sich zu Beths Elternhaus. Dort t\u00f6ten sie auf bestialische Weise Skyes Eltern und entf\u00fchren Skye. Zu Hause stellt sie Stanley zur Rede. Sie bet\u00e4uben ihn und schlie\u00dfen ihn ein. Stanley gelingt allerdings die Flucht und er t\u00f6tet Samantha. Alan kann ihn jedoch wieder bes\u00e4nftigen und die beiden t\u00f6ten alle Patienten der Klinik. Anschlie\u00dfend stellen sie Beth eine Falle im Hospital aus dem 1. Teil.\nBeth kommt jedoch vorher an und trifft dort Scott Tepperman, der als einziger f\u00fcr die Morde aus dem ersten Teil verurteilt wurde. Mit ihm zusammen stellen sie sich Alan und Daniel. W\u00e4hrend Stanley versucht Skye vorzubereiten, gelingt dieser jedoch die Flucht. W\u00e4hrend die beiden k\u00e4mpfen, \u00fcberrumpeln Beth und Scott Alan. Scott vergewaltigt ihn daraufhin. Als Beth h\u00f6rt, wie sich jemand n\u00e4hert, schie\u00dft sie im Glauben es handele sich um Stanley. Sie trifft jedoch Skye, die auf der Stelle tot ist. Im darauffolgenden Showdown t\u00f6ten die \u00dcberlebenden sich gegenseitig. Scott \u00fcberlebt als einziger und wird erneut festgenommen.\n"
}