{
    "date": "03-05-2021 12:32:33",
    "link": "https://de.wikipedia.org/wiki/Der%5FFroschk%C3%B6nig%5F%281954%29",
    "title": "Der Froschk\u00f6nig (1954)",
    "category": "M\u00e4rchenfilm",
    "text": "\nDer Froschk\u00f6nig ist ein deutscher M\u00e4rchenfilm von Otto Meyer aus dem Jahr 1954. Er beruht auf dem M\u00e4rchen Der Froschk\u00f6nig oder der eiserne Heinrich und ist mit musikalischen Beitr\u00e4gen versehen. Die Hauptrollen sind mit Olga Limburg als K\u00f6niginmutter, Stanislav Ledinek als K\u00f6nig, Dorothea Wieck als F\u00fcrstin Than, Marion Elisabeth Degler, Siglinde K\u00f6nig und Ruth Nimbach als die drei Prinzessinnen, Hans Kwiet als Prinz Edelmut und Franz Nicklisch als treuem Diener Heinrich besetzt.\nDie deutsche Erstausstrahlung der Schwarzwei\u00df-Produktion erfolgte am 25. Dezember 1954.\nPrinz Edelmuts schwerkranker Vater verf\u00fcgt, dass sein Sohn ab seinem 21. Lebensjahr die Amtsgesch\u00e4fte \u00fcbernehmen soll und solange der Diener Heinrich treu an seiner Seite zu bleiben habe. Um seinem sterbenden Vater das Leben zu retten, will Prinz Edelmut einen Zaubertrank beschaffen, den die F\u00fcrstin Than besitzt. Da sie als b\u00f6se Fee bekannt ist, warnt ihn sein Vater, sich unn\u00f6tig in Gefahr zu begeben. Dennoch reitet der Prinz los, wird jedoch von der F\u00fcrstin zur\u00fcckgewiesen, die ihm ihre Hilfe versagt. Als er nicht nachgibt und sie ber\u00fchrt, verwandelt sie ihn in einen Frosch. Diener Heinrich, der die F\u00fcrstin daraufhin anfleht, seinen Prinzen wieder zur\u00fcckzuverwandeln, wird ebenfalls zur\u00fcckgewiesen. Die F\u00fcrstin gibt lediglich bekannt, dass der Prinz nur von einem guten, tugendhaften Menschenkind und durch einen Kuss wieder erl\u00f6st werden k\u00f6nne.\nIn einem nahe gelegenen K\u00f6nigreich feiert Prinzessin Susanne ihren sechzehnten Geburtstag. Unter ihren Geschenken befindet sich ein Spiel, das sich ihr alter Diener Johann ausgedacht hat. Dabei handelt es sich um einen Fangbecher, mit dem man eine Kugel in die Luft wirft und dann wieder auffangen muss. Ihr Vater, der K\u00f6nig, hat ihr daf\u00fcr extra eine goldene Kugel gestiftet. Als sie das Spiel im Park ausprobiert, h\u00f6rt sie Hilferufe in der N\u00e4he des Schlossteichs. Doch niemand von ihren Bediensteten kann die Stimme h\u00f6ren. So machen sie sich Gedanken \u00fcber den Gesundheitszustand der Prinzessin und auch deren Schwestern finden das Verhalten Susannes recht seltsam. Sicherheitshalber l\u00e4sst der K\u00f6nig seine Tochter von seinem Hofarzt untersuchen, der jedoch nichts feststellen kann und vorschl\u00e4gt, sie unter Beobachtung zu stellen. Als die Prinzessin am n\u00e4chsten Tag wieder am Schlossteich spielt und abermals die Hilferufe h\u00f6rt, entdeckt sie einen Frosch und macht sich Sorgen um sein Leben, da sie auch eine Schlange entdecken kann. Da aber wieder kein anderer die Stimme vernommen hat, zweifelt man zunehmend am geistigen Zustand der Prinzessin. Der alte Diener Johann kennt allerdings die Geschichte von Prinz Edelmut, der vor f\u00fcnf Jahren in einen Frosch verwandelt worden sein soll. Er erz\u00e4hlt seinem Enkel davon, der als Page im Schloss arbeitet. Dabei werden sie von Peter, einem anderen Pagen, belauscht, der Prinzessin Sieglinde davon erz\u00e4hlt. Diese ist ganz versessen darauf, Prinz Edelmut zu erl\u00f6sen und so begibt sie sich noch in der Nacht hinunter zum See. Doch auch ihre Schwester Sophie erf\u00e4hrt davon und will ebenfalls zum See. Nach dem Frosch rufend, h\u00f6ren sich die Schwestern gegenseitig und halten jeweils die andere f\u00fcr den verwunschenen Prinzen. Dabei geraten sie in den stinkenden Morast und kehren jammernd wieder ins Schloss zur\u00fcck.\nAm n\u00e4chsten Tag h\u00e4lt sich Prinzessin Susanne mit ihrem neuen Spiel wieder am See auf, dabei f\u00e4llt die goldenen Kugel ins Wasser und w\u00e4hrend sie noch \u00fcberlegt, wie sie sie aus dem tiefen Wasser holen k\u00f6nne, h\u00f6rt sie wieder eine Stimme die sagt: \u201eIch kann Dir helfen, K\u00f6nigskind, ich kann Dir helfen.\u201c Da entdeckt sie den Frosch, der ihr verspricht, die Kugel aus dem tiefen See heraufzuholen, wenn sie ihn k\u00fcssen werde, er ihr Spielkamerad sein, von ihrem Teller essen und aus ihrem Becher trinken d\u00fcrfe. Die Prinzessin willigt in die Bedingungen ein. \nSowohl Diener Johann, als auch Page Philipp waren mit am See, doch sie konnten die Stimme nicht h\u00f6ren, trotzdem ist Johann davon \u00fcberzeugt, dass dieser Frosch Prinz Edelmut sei und so bastelt er ihm eine kleine Krone, die er ihm aufsetzt, als der Frosch sich tats\u00e4chlich im Schloss erscheint, um seinen Lohn einzufordern. Vor dem herrschaftlichen Zimmer angekommen, ruft er: \u201eK\u00f6nigstochter, J\u00fcngste, macht mir auf!\u201c Zun\u00e4chst z\u00f6gert Prinzessin Susanne, doch als ihr Vater ihr erkl\u00e4rt, dass man Versprechen einhalten m\u00fcsse, \u00f6ffnet sie die T\u00fcr und l\u00e4sst den ihn herein. Ihre beiden \u00e4lteren Schwestern sind allerdings emp\u00f6rt \u00fcber den ekligen Gast an ihrer Tafel, der nun auch bittet, vom Teller der Prinzessin zu essen und aus ihrem Becher trinken zu d\u00fcrfen. Als sie mit ihm auf ihr Zimmer gehen will, ist der Frosch pl\u00f6tzlich verschwunden. Aber Johann hat ihn sicher verwahrt und bringt ihn zu Susanne, die nun ihr letztes Versprechen einl\u00f6st und den Frosch k\u00fcsst. Daraufhin verwandelt sich das Tier zur\u00fcck in den jungen Prinzen, der sich bei den Dienern bedankt, dass sie ihn so gut besch\u00fctzt haben. Alsdann bedankt er sich beim K\u00f6nig und bittet ihn um die Hand seiner j\u00fcngsten Tochter. Zun\u00e4chst will er jedoch zur\u00fcck in sein K\u00f6nigreich. Er werde in etwa einer Woche zur\u00fcckkommen, um Prinzessin Susanne zu heiraten, versichert er.\nNach neun Tagen erscheint Diener Heinrich und k\u00fcndigt das Kommen seines Herrn an, der Prinzessin Susanne in seine Kutsche bittet und zusammen mit ihren Dienern Johann und Philipp in sein K\u00f6nigreich zur\u00fcckkehrt, wo die Hochzeit stattfinden soll. Auf der Fahrt dorthin wird der Prinz von einem heftigen Ger\u00e4usch erschreckt, sodass er ausruft: \u201eHeinrich, der Wagen bricht\u201c. Doch der Diener antwortet: \u201eNein Herr, es ist ein Band von meinem Herzen\u201c, denn er hatte sich vor f\u00fcnf Jahren drei eiserne B\u00e4nder um seine Brust schmieden lassen damit er:\nDas Ganze geschieht noch zweimal, bis auch das letzte Band die Brust des treuen Dieners Heinrich wieder freigibt.\nDer Film wurde in einem behelfsm\u00e4\u00dfigen Atelier im Schloss Charlottenburg produziert. Die Au\u00dfenaufnahmen entstanden im Schlosspark Charlottenburg. Karl Vollbrecht schuf die Bauten, Produzent Bernhard F. Schmidt war zugleich Produktionsleiter.\nDie Schwarzwei\u00df-Produktion ist mit musikalischen Beitr\u00e4gen untermalt, so tr\u00e4gt Page Philipp als Minnes\u00e4nger in einem Sprechgesang einleitend die Geschichte als Ballade vor. Weitere Liedbeitr\u00e4ge der Prinzessin und der Hofwache folgen.\nDer Hauptteil der Verfilmung besch\u00e4ftigt sich mit dem Leben am Hof der Prinzessin und wie die Bediensteten versuchen festzustellen, ob es wirklich Hilferufe am See gibt, oder ob ihre Prinzessin wirr im Kopf ist. Alle Frosch-Szenen werden durch einen echten Frosch dargestellt.\n\u201eDas Grimmsche M\u00e4rchen in einer kindgerechten und schauspielerisch beachtlichen 50er-Jahre-Fassung.\u201c\n"
}