{
    "date": "03-05-2021 12:10:39",
    "link": "https://de.wikipedia.org/wiki/Hard%5FRevenge%5FMilly%5F%E2%80%93%5FThe%5FBeginning",
    "title": "Hard Revenge Milly \u2013 The Beginning",
    "category": "Splatterfilm",
    "text": "\nHard Revenge Milly \u2013 The Beginning (jap. \u30cf\u30fc\u30c9\u30ea\u30d9\u30f3\u30b8\u30fb\u30df\u30ea\u30fc, H\u0101do Ribenji Mir\u012b) ist ein japanischer Kurzfilm von  Takanori Tsujimoto aus dem Jahr 2008. Der Splatter-Actionfilm ist der Vorg\u00e4nger des Langfilms Hard Revenge Milly \u2013 Bloody Battle (2009).\nIn einer postapokalyptischen Zukunft regieren Gangs die Stra\u00dfen. Die junge Frau Milly wurde bei einem \u00dcberfall der vierk\u00f6pfigen Gang Jack Brothers schwer verletzt, w\u00e4hrend ihr Mann und Kind auf grauenhafte Weise ermordet wurden. Milly \u00fcberlebte den Angriff und schwor Rache. Der zur\u00fcckgezogen lebende ehemalige Waffenh\u00e4ndler Jubei las die junge Frau auf und modifizierte ihren K\u00f6rper zu einer todbringenden Waffe. Nacheinander t\u00f6tet Milly die vier Jack Brothers und nimmt so Rache f\u00fcr ihre ermordete Familie.\nEin Jahr sp\u00e4ter erschien die Fortsetzung Hard Revenge Milly \u2013 Bloody Battle, diesmal als Langfilm mit gleicher Hauptdarstellerin. Der Film ist im Stil popul\u00e4rer Japan-Splatterfilme wie The Machine Girl und Tokyo Gore Police gehalten. Die Effekte stammen von Yoshihiro Nishimura, der ebenfalls f\u00fcr die Effekte der beiden vorgenannten Filme verantwortlich zeichnet.\nIn \u00d6sterreich erschien \u00fcber Dragon eine ungek\u00fcrzte, auf 1.500 St\u00fcck limitierte DVD unter dem Titel Hard Revenge Milly ausgezeichnet als \u201eGrindhouse Double Feature DVD\u201c, die beide Filme sowie zwei Making-ofs enth\u00e4lt.\nHard Revenge Milly \u2013 The Beginning  setzt auf wenig Story und viele Splatterffekte. Dabei heben sich die Kampfszenen des B-Films von denen anderer Produktionen ab.\n"
}